[
	{
		"__TYPE__": "SharedSliceContent",
		"variation": "accordion_with_title",
		"primary": {
			"section_title": {
				"__TYPE__": "StructuredTextContent",
				"value": [
					{
						"type": "heading2",
						"content": {
							"text": "Better"
						}
					}
				]
			},
			"items": {
				"__TYPE__": "GroupContentType",
				"value": [
					{
						"__TYPE__": "GroupItemContent",
						"value": [
							[
								"item_title",
								{
									"__TYPE__": "FieldContent",
									"value": "loss",
									"type": "Text"
								}
							],
							[
								"item_content",
								{
									"__TYPE__": "StructuredTextContent",
									"value": [
										{
											"type": "paragraph",
											"content": {
												"text": "Ut cupidatat nisi ea. Incididunt duis aliqua excepteur duis et reprehenderit aliqua laboris eu minim minim."
											}
										}
									]
								}
							]
						]
					}
				]
			}
		},
		"items": []
	}
]